{
  "format_version": "1.12",
  "minecraft:recipe_shaped": {
    "description": {
    "identifier": "absolute_guns_craft:mp5"
    },

    
    "tags": [ "crafting_table" ],
    "pattern": [
      "B  ",
      " I ",
      "A H"
    ],
    "key": {
      "H": {
        "item": "minecraft:iron_hoe"
      },
      "I": {
        "item": "minecraft:iron_ingot"
      },
      "B": {
        "item": "minecraft:iron_bars"
      },
      "A": {
        "item": "absolute_guns:smg_ammo"
      }
    },
    "result": {
      "item": "absolute_guns:mp5"
    }
  }
}
